ERIS_API/__init__.py
ERIS_API/ERIS_API.py
ERIS_API/ERIS_Parameters.py
ERIS_API/ERIS_Responses.py
ERIS_API/models.py
ERIS_API/utils.py
eris_api-1.5.1.dist-info/LICENSE
eris_api-1.5.1.dist-info/WHEEL
eris_api-1.5.1.dist-info/METADATA
eris_api-1.5.1.dist-info/RECORD
